LICENSE
MANIFEST.in
README.rst
requirements.txt
setup.cfg
setup.py
putiosync/__init__.py
putiosync/core.py
putiosync/dbmodel.py
putiosync/download_manager.py
putiosync/frontend.py
putiosync/multipart_downloader.py
putiosync.egg-info/PKG-INFO
putiosync.egg-info/SOURCES.txt
putiosync.egg-info/dependency_links.txt
putiosync.egg-info/entry_points.txt
putiosync.egg-info/requires.txt
putiosync.egg-info/top_level.txt
putiosync/webif/__init__.py
putiosync/webif/webif.py
putiosync/webif/static/css/bootstrap-theme.css
putiosync/webif/static/css/bootstrap-theme.min.css
putiosync/webif/static/css/bootstrap.css
putiosync/webif/static/css/bootstrap.min.css
putiosync/webif/static/js/bootstrap.js
putiosync/webif/static/js/bootstrap.min.js
putiosync/webif/static/js/handlebars-v1.3.0.js
putiosync/webif/static/js/jquery.flot.js
putiosync/webif/templates/active.html
putiosync/webif/templates/base.html
putiosync/webif/templates/history.html
putiosync/webif/templates/macros.html